odoo/addons/partner_manual_rank/README.rst
odoo/addons/partner_manual_rank/__init__.py
odoo/addons/partner_manual_rank/__manifest__.py
odoo/addons/partner_manual_rank/i18n/es.po
odoo/addons/partner_manual_rank/i18n/fr.po
odoo/addons/partner_manual_rank/i18n/it.po
odoo/addons/partner_manual_rank/i18n/partner_manual_rank.pot
odoo/addons/partner_manual_rank/i18n/pt.po
odoo/addons/partner_manual_rank/models/__init__.py
odoo/addons/partner_manual_rank/models/res_partner.py
odoo/addons/partner_manual_rank/readme/CONTRIBUTORS.rst
odoo/addons/partner_manual_rank/readme/DESCRIPTION.rst
odoo/addons/partner_manual_rank/static/description/icon.png
odoo/addons/partner_manual_rank/static/description/index.html
odoo/addons/partner_manual_rank/tests/__init__.py
odoo/addons/partner_manual_rank/tests/test_res_partner.py
odoo/addons/partner_manual_rank/views/res_partner.xml
odoo14_addon_partner_manual_rank-14.0.1.2.0.dist-info/METADATA
odoo14_addon_partner_manual_rank-14.0.1.2.0.dist-info/WHEEL
odoo14_addon_partner_manual_rank-14.0.1.2.0.dist-info/top_level.txt
odoo14_addon_partner_manual_rank-14.0.1.2.0.dist-info/RECORD
